ConsenSys_Utils-0.1.0.dist-info/METADATA
ConsenSys_Utils-0.1.0.dist-info/RECORD
ConsenSys_Utils-0.1.0.dist-info/WHEEL
ConsenSys_Utils-0.1.0.dist-info/top_level.txt
consensys_utils/__init__.py
consensys_utils/logging.py
consensys_utils/wsgi.py
consensys_utils/config/__init__.py
consensys_utils/config/loader.py
consensys_utils/config/schema/__init__.py
consensys_utils/config/schema/flask.py
consensys_utils/config/schema/gunicorn.py
consensys_utils/config/schema/logging.py
consensys_utils/config/schema/wsgi.py
consensys_utils/flask/__init__.py
consensys_utils/flask/app.py
consensys_utils/flask/blueprints.py
consensys_utils/flask/cli.py
consensys_utils/flask/config.py
consensys_utils/flask/hooks.py
consensys_utils/flask/logging.py
consensys_utils/flask/wsgi.py
consensys_utils/flask/extensions/__init__.py
consensys_utils/flask/extensions/health.py
consensys_utils/flask/extensions/swagger.py
consensys_utils/gunicorn/__init__.py
consensys_utils/gunicorn/app.py
consensys_utils/gunicorn/config.py
consensys_utils/gunicorn/logging.py
tests/__init__.py
tests/conftest.py
tests/helpers.py
tests/test_import.py
tests/test_logging.py
tests/config/__init__.py
tests/config/conftest.py
tests/config/test_loader.py
tests/config/test_schema.py
tests/flask/__init__.py
tests/flask/conftest.py
tests/flask/test_app.py
tests/flask/test_blueprints.py
tests/flask/test_cli.py
tests/flask/test_config.py
tests/flask/test_extensions.py
tests/flask/test_hooks.py
tests/flask/test_logging.py
tests/flask/test_wsgi.py
tests/gunicorn/__init__.py
tests/gunicorn/conftest.py
tests/gunicorn/test_app.py
tests/gunicorn/test_config.py
tests/gunicorn/test_logging.py
tests/gunicorn/test_schema.py
