Metadata-Version: 2.1
Name: ConsenSys-Utils
Version: 0.1.0
Summary: A set of utility resources used on a daily basis by ConsenSys France Engineering team
Home-page: https://github.com/ConsenSys/consensys-utils
Author: Nicolas Maurice
Author-email: nicolas.maurice@consensys.net
Maintainer: ConsenSys France
License: Copyright (c) 2017 by ConsenSys France and contributors.
Provides-Extra: all
Requires-Dist: cfg-loader (>=0.2.2); extra == 'all'
Requires-Dist: flask (>=1.0.0); extra == 'all'
Requires-Dist: flask-restful (>=0.3.6); extra == 'all'
Requires-Dist: flasgger (>=0.8.0); extra == 'all'
Requires-Dist: healthcheck (>=1.3.0); extra == 'all'
Requires-Dist: gunicorn (>=19.9.0); extra == 'all'
Provides-Extra: config
Requires-Dist: cfg-loader (>=0.2.2); extra == 'config'
Provides-Extra: dev
Requires-Dist: flake8; extra == 'dev'
Requires-Dist: autoflake; extra == 'dev'
Requires-Dist: autopep8; extra == 'dev'
Requires-Dist: coverage; extra == 'dev'
Requires-Dist: pytest (>=3); extra == 'dev'
Requires-Dist: pytest-flask; extra == 'dev'
Requires-Dist: tox; extra == 'dev'
Requires-Dist: sphinx; extra == 'dev'
Requires-Dist: sphinx-rtd-theme; extra == 'dev'
Provides-Extra: doc
Requires-Dist: sphinx; extra == 'doc'
Requires-Dist: sphinx-rtd-theme; extra == 'doc'
Provides-Extra: flask
Requires-Dist: cfg-loader (>=0.2.2); extra == 'flask'
Requires-Dist: flask (>=1.0.0); extra == 'flask'
Requires-Dist: flask-restful (>=0.3.6); extra == 'flask'
Requires-Dist: flasgger (>=0.8.0); extra == 'flask'
Requires-Dist: healthcheck (>=1.3.0); extra == 'flask'
Requires-Dist: gunicorn (>=19.9.0); extra == 'flask'
